crackers-0.9.0.dist-info/METADATA
crackers-0.9.0.dist-info/WHEEL
crackers/__init__.py
crackers/_internal.cpython-314-x86_64-linux-gnu.so
crackers/_internal.pyi
crackers/config/__init__.py
crackers/config/constraint.py
crackers/config/crackers.py
crackers/config/library.py
crackers/config/log_level.py
crackers/config/meta.py
crackers/config/sleigh.py
crackers/config/specification.py
crackers/config/synthesis.py
crackers/crackers.py
crackers/crackers.pyi
crackers/jingle.py
crackers/jingle.pyi
crackers/py.typed
crackers-0.9.0.dist-info/RECORD
