Metadata-Version: 2.4
Name: crackers
Version: 0.9.0
Classifier: Programming Language :: Rust
Classifier: Programming Language :: Python :: Implementation :: CPython
Classifier: Programming Language :: Python :: Implementation :: PyPy
Requires-Dist: pydantic>=2.10.6
Requires-Dist: z3-solver==4.15.3.0
Requires-Dist: ruff ; extra == 'dev'
Requires-Dist: mypy ; extra == 'dev'
Requires-Dist: nox ; extra == 'dev'
Requires-Dist: z3-solver ; extra == 'dev'
Requires-Dist: pydantic>=2.10.6 ; extra == 'dev'
Provides-Extra: dev
Requires-Python: >=3.10
